vfsm/__init__.py
vfsm-0.1.dist-info/LICENSE
vfsm-0.1.dist-info/METADATA
vfsm-0.1.dist-info/WHEEL
vfsm-0.1.dist-info/top_level.txt
vfsm-0.1.dist-info/RECORD
